my_joke_not_good/__init__.py
my_joke_not_good-0.1.dist-info/METADATA
my_joke_not_good-0.1.dist-info/WHEEL
my_joke_not_good-0.1.dist-info/top_level.txt
my_joke_not_good-0.1.dist-info/RECORD
